s3_object_validator/__init__.py
s3_object_validator/__main__.py
s3_object_validator/validator.py
tests/__init__.py
tests/test_s3_object_validator.py
s3_object_validator-0.0.2.dist-info/LICENSE
s3_object_validator-0.0.2.dist-info/METADATA
s3_object_validator-0.0.2.dist-info/WHEEL
s3_object_validator-0.0.2.dist-info/entry_points.txt
s3_object_validator-0.0.2.dist-info/top_level.txt
s3_object_validator-0.0.2.dist-info/RECORD
