Metadata-Version: 2.1
Name: s3-object-validator
Version: 0.0.2
Summary: Validator for S3 object key names
Home-page: https://github.com/sgcooper78/s3_object_validator
Author: Scott Cooper
Author-email: sgcooper78@gmail.com
Keywords: python,aws,s3
Classifier: Programming Language :: Python :: 3
Classifier: License :: OSI Approved :: GNU Affero General Public License v3
Classifier: Operating System :: OS Independent
License-File: LICENSE
